omero_figure/__init__.py
omero_figure/apps.py
omero_figure/omeroutils.py
omero_figure/settings.py
omero_figure/urls.py
omero_figure/utils.py
omero_figure/views.py
omero_figure/__pycache__/__init__.cpython-310.pyc
omero_figure/__pycache__/utils.cpython-310.pyc
omero_figure/scripts/omero/figure_scripts/Figure_To_Pdf.py
omero_figure/static/omero_figure/bootstrap-icons.css
omero_figure/static/omero_figure/index.html
omero_figure/static/omero_figure/assets/index-DoUBPzH4.css
omero_figure/static/omero_figure/assets/index-kpUECZPf.js
omero_figure/static/omero_figure/assets/index-kpUECZPf.js.map
omero_figure/static/omero_figure/assets/luts_10-CgN3hjir.png
omero_figure/static/omero_figure/fonts/bootstrap-icons.woff2
omero_figure/templates/omero_figure/index.html
omero_figure-7.3.1.dist-info/licenses/LICENSE
omero_figure-7.3.1.dist-info/METADATA
omero_figure-7.3.1.dist-info/WHEEL
omero_figure-7.3.1.dist-info/top_level.txt
omero_figure-7.3.1.dist-info/RECORD
